wiserHeatingAPI/__init__.py
wiserHeatingAPI/wiserHub.py
wiser_heating_api-1.0.0.dist-info/LICENSE
wiser_heating_api-1.0.0.dist-info/METADATA
wiser_heating_api-1.0.0.dist-info/WHEEL
wiser_heating_api-1.0.0.dist-info/top_level.txt
wiser_heating_api-1.0.0.dist-info/RECORD
