Metadata-Version: 2.1
Name: wiser-heating-api
Version: 1.0.0
Summary: A simple API for accessing data on the Drayton Wiser Heating system
Home-page: https://github.com/asantaga/wiserheatingapi
Author: Angelo Santagata
Author-email: angelosantagata@gmail.com
License: UNKNOWN
Platform: UNKNOWN
Classifier: Programming Language :: Python :: 3
Classifier: License :: OSI Approved :: MIT License
Classifier: Operating System :: OS Independent
